appodeal/__init__.py
appodeal/admin.py
appodeal/apps.py
appodeal/models.py
appodeal/tests.py
appodeal/urls.py
appodeal/views.py
appodeal/migrations/0001_initial.py
appodeal/migrations/__init__.py
appodeal-0.9.3.dist-info/DESCRIPTION.rst
appodeal-0.9.3.dist-info/METADATA
appodeal-0.9.3.dist-info/RECORD
appodeal-0.9.3.dist-info/WHEEL
appodeal-0.9.3.dist-info/metadata.json
appodeal-0.9.3.dist-info/top_level.txt
tests/__init__.py
tests/handler.py
tests/settings.py
tests/urls.py
