Metadata-Version: 2.0
Name: appodeal
Version: 0.9.3
Summary: Django views for Appodeal integration
Home-page: https://github.com/alej0varas/djappodeal
Author: Alexandre Varas
Author-email: alej0varas@gmail.com
License: GPL v3
Keywords: django appodeal reward
Platform: UNKNOWN
Classifier: Topic :: Internet :: WWW/HTTP :: Dynamic Content
Classifier: Intended Audience :: Developers
Classifier: Programming Language :: Python
Classifier: Programming Language :: Python :: 3
Classifier: Programming Language :: Python :: 3.2
Classifier: Programming Language :: Python :: 3.3
Classifier: Programming Language :: Python :: 3.4
Classifier: Programming Language :: Python :: 3.5
Classifier: Framework :: Django
Classifier: Framework :: Django :: 1.10
Classifier: Framework :: Django :: 1.11
Classifier: Development Status :: 4 - Beta
Classifier: Operating System :: OS Independent
Requires-Dist: django
Requires-Dist: pycrypto
